GearMess_client-0.3.2.dist-info/METADATA
GearMess_client-0.3.2.dist-info/RECORD
GearMess_client-0.3.2.dist-info/WHEEL
GearMess_client-0.3.2.dist-info/entry_points.txt
GearMess_client-0.3.2.dist-info/top_level.txt
client_src/__init__.py
client_src/client.py
client_src/client_gui.py
client_src/client_models.py
client_src/client_storage_handler.py
client_src/client_views.py
client_src/console_client.py
client_src/JIM/JIMs.py
client_src/JIM/__init__.py
client_src/JIM/jim_config.py
client_src/crypto/__init__.py
client_src/crypto/crypto.py
