Metadata-Version: 2.1
Name: GearMess-client
Version: 0.3.2
Summary: Simple messenger.
Home-page: https://github.com/StanislavAntunovich/GearMess
Author: StanislavAntunovich
Author-email: stanislav.antunovich@yandex.ru
License: MIT
Keywords: python,messenger
Platform: UNKNOWN
Requires-Dist: PyQt5
Requires-Dist: SQLAlchemy
Requires-Dist: pycryptodomex
